temsah/__init__.py
temsah/currency.py
temsah/data_extractor.py
temsah/main.py
temsah-2.1.6.dist-info/LICENSE.txt
temsah-2.1.6.dist-info/METADATA
temsah-2.1.6.dist-info/WHEEL
temsah-2.1.6.dist-info/top_level.txt
temsah-2.1.6.dist-info/RECORD
