Metadata-Version: 2.1
Name: temsah
Version: 2.1.6
Summary: Temsah is a powerful Python library specifically designed for web scraping e-commerce platforms such as Amazon.
Author: sahel seyedyazdi
Author-email: seyedsahel1383@gmail.com
License-File: LICENSE.txt
Requires-Dist: requests
Requires-Dist: BeautifulSoup4
Requires-Dist: chardet
